<PAMDataset>
  <Metadata>
    <MDI key="DataType">Generic</MDI>
  </Metadata>
  <Metadata domain="Esri">
    <MDI key="PyramidResamplingType">NEAREST</MDI>
  </Metadata>
  <PAMRasterBand band="1">
    <Histograms>
      <HistItem>
        <HistMin>1568</HistMin>
        <HistMax>3463</HistMax>
        <BucketCount>256</BucketCount>
        <IncludeOutOfRange>1</IncludeOutOfRange>
        <Approximate>0</Approximate>
        <HistCounts>3079|7323|11435|7810|11187|14275|16661|17713|16981|18609|18254|16562|16496|17127|11873|13154|18352|20193|21602|17263|20719|16986|18867|22620|17494|24211|23208|27037|29564|24956|37233|31971|36543|43505|46488|46455|44344|46937|46524|55110|52815|64006|78361|104341|104595|93069|112018|86395|106947|151383|154509|507438|317894|321114|316957|343345|201503|215712|225995|410041|522806|463523|553501|529023|407465|315987|271327|297486|304333|322517|272936|359477|318893|315563|367240|331982|366116|378180|407717|390164|378462|423785|418394|514521|559140|664130|639525|735137|721758|766339|805191|671403|762262|652706|847277|881293|836889|947038|839115|978605|897380|838723|1005995|949114|1179869|1207344|6207764|1656098|2396089|1987396|1942299|1950590|1868157|1917288|1668430|1783332|1600422|1657399|1704524|1541846|1675921|1580782|1908655|1770376|1672607|1764017|1635620|1821249|1673770|1722951|1754525|1763843|1870470|1670453|1696616|1596049|1485784|1392848|1354467|1230228|1149093|1129005|923007|956542|778689|781390|819160|700053|781100|670925|730795|684232|620107|678458|523997|534375|479537|478145|455528|483671|412372|421498|415345|394157|400953|330416|371259|306923|313993|337530|284990|328128|265355|280066|252486|231624|267386|214593|231434|210314|208939|186534|166468|176936|155008|156170|141773|147790|123911|121798|121976|109407|112714|96240|103871|85080|81928|83549|69320|72374|56046|59714|49732|46312|51170|40695|44310|37931|39010|32973|33274|26948|25998|26009|22102|22438|19154|22152|16812|15370|14887|11335|11663|8789|9594|8164|7292|8108|6271|8128|5962|5628|4342|3431|3348|2116|1626|1398|1155|730|539|608|306|166|137|106|68|74|87|82|80|40|42|31|22|2</HistCounts>
      </HistItem>
    </Histograms>
    <Metadata>
      <MDI key="RepresentationType">ATHEMATIC</MDI>
      <MDI key="STATISTICS_COVARIANCES">51807.92913526974</MDI>
      <MDI key="STATISTICS_EXCLUDEDVALUES"></MDI>
      <MDI key="STATISTICS_MAXIMUM">3463</MDI>
      <MDI key="STATISTICS_MEAN">2446.8034560838</MDI>
      <MDI key="STATISTICS_MEDIAN">2444.901961</MDI>
      <MDI key="STATISTICS_MINIMUM">1568</MDI>
      <MDI key="STATISTICS_SKIPFACTORX">1</MDI>
      <MDI key="STATISTICS_SKIPFACTORY">1</MDI>
      <MDI key="STATISTICS_STDDEV">227.6135521784</MDI>
    </Metadata>
  </PAMRasterBand>
</PAMDataset>
